logos_lang/Logos.g4
logos_lang/LogosLexerRules.g4
logos_lang/__init__.py
logos_lang/__main__.py
logos_lang/assemble_link.sh
logos_lang/conftest.py
logos_lang/make.sh
logos_lang/program.as
logos_lang/program.as.ast
logos_lang/requirements.txt
logos_lang/.vscode/launch.json
logos_lang/IL/ILGenerator.py
logos_lang/IL/RegisterAllocator.py
logos_lang/IL/__init__.py
logos_lang/codegen/__init__.py
logos_lang/codegen/arm/__init__.py
logos_lang/codegen/arm/templates.py
logos_lang/consts/__init__.py
logos_lang/generated/Logos.interp
logos_lang/generated/Logos.tokens
logos_lang/generated/LogosLexer.interp
logos_lang/generated/LogosLexer.py
logos_lang/generated/LogosLexer.tokens
logos_lang/generated/LogosListener.py
logos_lang/generated/LogosParser.py
logos_lang/generated/LogosVisitor.py
logos_lang/notes/NOTES.md
logos_lang/notes/assembly/hello_world
logos_lang/notes/assembly/hello_world.as
logos_lang/notes/assembly/hello_world.o
logos_lang/programs/1.l
logos_lang/programs/2.l
logos_lang/programs/3.l
logos_lang/programs/fib.l
logos_lang/programs/hello_world.l
logos_lang/programs/rand.l
logos_lang/programs/ref.l
logos_lang/programs/reg_alloc.l
logos_lang/programs/if_else/1.l
logos_lang/programs/mem/1.l
logos_lang/programs/spill/1.l
logos_lang/programs/spill/2.l
logos_lang/programs/spill/3.l
logos_lang/programs/while/1.l
logos_lang/tests/RegisterAllocator/test_generates_liveness.py
logos_lang/tests/RegisterAllocator/test_graph_coloring.py
logos_lang/tests/RegisterAllocator/test_kill.py
logos_lang/tests/RegisterAllocator/test_liveness_analysis.py
logos_lang/tests/RegisterAllocator/test_spilling.py
logos_lang/tests/RegisterAllocator/test_successors.py
logos_lang/tests/utils/test_graph.py
logos_lang/tests/utils/test_math.py
logos_lang/utils/__init__.py
logos_lang/utils/graph.py
logos_lang/utils/math.py
logos_lang-0.0.1.dist-info/METADATA
logos_lang-0.0.1.dist-info/WHEEL
logos_lang-0.0.1.dist-info/entry_points.txt
logos_lang-0.0.1.dist-info/licenses/LICENSE
logos_lang-0.0.1.dist-info/RECORD
